nate_indi/__init__.py
nate_indi/macd.py
nate_indi-0.2.dist-info/LICENSE
nate_indi-0.2.dist-info/METADATA
nate_indi-0.2.dist-info/WHEEL
nate_indi-0.2.dist-info/entry_points.txt
nate_indi-0.2.dist-info/top_level.txt
nate_indi-0.2.dist-info/RECORD
