Metadata-Version: 2.1
Name: nate-indi
Version: 0.2
Summary: A Python package for making API requests
Home-page: https://github.com/my-username/my-package
Author: My Name
Author-email: myemail@example.com
License: MIT
License-File: LICENSE
Requires-Dist: pandas-ta
